<annotation>
	<folder></folder>
	<filename>134f5306-679b-11e5-af8c-40f2e96c8ad8_jpg.rf.1cf370996758b68d69e2cfb1c775e5f0.jpg</filename>
	<path>134f5306-679b-11e5-af8c-40f2e96c8ad8_jpg.rf.1cf370996758b68d69e2cfb1c775e5f0.jpg</path>
	<source>
		<database>roboflow.com</database>
	</source>
	<size>
		<width>640</width>
		<height>640</height>
		<depth>3</depth>
	</size>
	<segmented>0</segmented>
	<object>
		<name>garbage</name>
		<pose>Unspecified</pose>
		<truncated>0</truncated>
		<difficult>0</difficult>
		<occluded>0</occluded>
		<bndbox>
			<xmin>2</xmin>
			<xmax>528</xmax>
			<ymin>85</ymin>
			<ymax>611</ymax>
		</bndbox>
	</object>
</annotation>
