<annotation>
	<folder></folder>
	<filename>images151_jpg.rf.42ffe78db5db8070e8683c0fa0f29efc.jpg</filename>
	<path>images151_jpg.rf.42ffe78db5db8070e8683c0fa0f29efc.jpg</path>
	<source>
		<database>roboflow.com</database>
	</source>
	<size>
		<width>640</width>
		<height>640</height>
		<depth>3</depth>
	</size>
	<segmented>0</segmented>
	<object>
		<name>garbage</name>
		<pose>Unspecified</pose>
		<truncated>0</truncated>
		<difficult>0</difficult>
		<occluded>0</occluded>
		<bndbox>
			<xmin>1</xmin>
			<xmax>237</xmax>
			<ymin>51</ymin>
			<ymax>328</ymax>
		</bndbox>
	</object>
	<object>
		<name>garbage</name>
		<pose>Unspecified</pose>
		<truncated>0</truncated>
		<difficult>0</difficult>
		<occluded>0</occluded>
		<bndbox>
			<xmin>225</xmin>
			<xmax>513</xmax>
			<ymin>154</ymin>
			<ymax>442</ymax>
		</bndbox>
	</object>
</annotation>
